{"mean":{"confidence_interval":{"confidence_level":0.95,"lower_bound":814557.639846395,"upper_bound":815275.6869545867},"point_estimate":814890.6200567394,"standard_error":183.4782707383749},"median":{"confidence_interval":{"confidence_level":0.95,"lower_bound":814305.6571428571,"upper_bound":814727.75},"point_estimate":814499.7723785166,"standard_error":98.55939226123039},"median_abs_dev":{"confidence_interval":{"confidence_level":0.95,"lower_bound":715.7592040885612,"upper_bound":1541.055956723237},"point_estimate":1128.7168712072057,"standard_error":198.7086585630382},"slope":{"confidence_interval":{"confidence_level":0.95,"lower_bound":814460.0252233499,"upper_bound":814908.432203245},"point_estimate":814674.0788724694,"standard_error":113.5716403588786},"std_dev":{"confidence_interval":{"confidence_level":0.95,"lower_bound":1224.5810309368524,"upper_bound":2535.758151151102},"point_estimate":1838.6040072229628,"standard_error":361.65838939914715}}