{"mean":{"confidence_interval":{"confidence_level":0.95,"lower_bound":822328.7115532974,"upper_bound":836479.0134192723},"point_estimate":827688.3117373788,"standard_error":3854.927443670157},"median":{"confidence_interval":{"confidence_level":0.95,"lower_bound":818225.7127659575,"upper_bound":819068.6319444445},"point_estimate":818589.1375,"standard_error":240.0085355392416},"median_abs_dev":{"confidence_interval":{"confidence_level":0.95,"lower_bound":1178.9658524022962,"upper_bound":2772.790695585198},"point_estimate":1656.739210552677,"standard_error":428.30917804117934},"slope":{"confidence_interval":{"confidence_level":0.95,"lower_bound":820452.5187026919,"upper_bound":824808.7453655304},"point_estimate":822484.4644066795,"standard_error":1112.2442110065867},"std_dev":{"confidence_interval":{"confidence_level":0.95,"lower_bound":8754.834290896895,"upper_bound":64640.9685887009},"point_estimate":38729.56611976042,"standard_error":18772.52652535895}}