{"mean":{"confidence_interval":{"confidence_level":0.95,"lower_bound":541793.6390636574,"upper_bound":543420.0109861966},"point_estimate":542517.3863379799,"standard_error":417.9658550300038},"median":{"confidence_interval":{"confidence_level":0.95,"lower_bound":542024.75,"upper_bound":542630.5147058824},"point_estimate":542505.8915566227,"standard_error":170.7605302077671},"median_abs_dev":{"confidence_interval":{"confidence_level":0.95,"lower_bound":797.1114920984586,"upper_bound":1622.248188789833},"point_estimate":1068.2291927776364,"standard_error":213.5583358011398},"slope":{"confidence_interval":{"confidence_level":0.95,"lower_bound":540720.5851009644,"upper_bound":541718.3426006702},"point_estimate":541204.7845766218,"standard_error":255.3607586892374},"std_dev":{"confidence_interval":{"confidence_level":0.95,"lower_bound":1847.6238508251092,"upper_bound":6343.718657711455},"point_estimate":4207.26892463935,"standard_error":1197.5971695422359}}