{"mean":{"confidence_interval":{"confidence_level":0.95,"lower_bound":423833.436386693,"upper_bound":431446.17431015405},"point_estimate":426848.44881674764,"standard_error":2016.8309160981737},"median":{"confidence_interval":{"confidence_level":0.95,"lower_bound":422695.1059795363,"upper_bound":423770.4756554307},"point_estimate":423190.24512987013,"standard_error":260.5466096027935},"median_abs_dev":{"confidence_interval":{"confidence_level":0.95,"lower_bound":1519.9954186940702,"upper_bound":3244.419395510105},"point_estimate":2079.765516864658,"standard_error":453.7249080435135},"slope":{"confidence_interval":{"confidence_level":0.95,"lower_bound":422889.3078676483,"upper_bound":424079.81238139264},"point_estimate":423410.825649968,"standard_error":303.27893153326283},"std_dev":{"confidence_interval":{"confidence_level":0.95,"lower_bound":4859.22860284294,"upper_bound":33247.81932268951},"point_estimate":20280.560802809356,"standard_error":8777.50641145179}}