{"mean":{"confidence_interval":{"confidence_level":0.95,"lower_bound":39267.696960950925,"upper_bound":40080.80326234366},"point_estimate":39573.610231838014,"standard_error":222.4639828525273},"median":{"confidence_interval":{"confidence_level":0.95,"lower_bound":39024.72020287405,"upper_bound":39047.56178396072},"point_estimate":39030.751502403844,"standard_error":6.163342671592977},"median_abs_dev":{"confidence_interval":{"confidence_level":0.95,"lower_bound":28.58108723358186,"upper_bound":94.32885228136708},"point_estimate":48.47588560406589,"standard_error":17.309004086381268},"slope":{"confidence_interval":{"confidence_level":0.95,"lower_bound":39156.2660807765,"upper_bound":39439.7651787398},"point_estimate":39287.242808084484,"standard_error":73.01553294154323},"std_dev":{"confidence_interval":{"confidence_level":0.95,"lower_bound":515.3858062070927,"upper_bound":3727.4500485565177},"point_estimate":2231.331830951339,"standard_error":1088.7556884726425}}