{"mean":{"confidence_interval":{"confidence_level":0.95,"lower_bound":906.9570041605044,"upper_bound":910.5402938475024},"point_estimate":908.4782560170559,"standard_error":0.9355621288471149},"median":{"confidence_interval":{"confidence_level":0.95,"lower_bound":906.7811561896499,"upper_bound":907.3258693353564},"point_estimate":907.0004924838875,"standard_error":0.14971017446911047},"median_abs_dev":{"confidence_interval":{"confidence_level":0.95,"lower_bound":1.4851776571302602,"upper_bound":2.828429933516548},"point_estimate":2.270435016436038,"standard_error":0.395724973757836},"slope":{"confidence_interval":{"confidence_level":0.95,"lower_bound":905.6884669092577,"upper_bound":906.6474162927832},"point_estimate":906.1349607007,"standard_error":0.24424539646776378},"std_dev":{"confidence_interval":{"confidence_level":0.95,"lower_bound":2.471838957073848,"upper_bound":14.690487892816508},"point_estimate":9.374790206416241,"standard_error":3.233497124526359}}