{"mean":{"confidence_interval":{"confidence_level":0.95,"lower_bound":269405.7125379746,"upper_bound":270042.7171902643},"point_estimate":269682.3641226836,"standard_error":164.82225174539624},"median":{"confidence_interval":{"confidence_level":0.95,"lower_bound":269322.71512681164,"upper_bound":269518.75},"point_estimate":269418.43314367,"standard_error":50.10897269484215},"median_abs_dev":{"confidence_interval":{"confidence_level":0.95,"lower_bound":355.09316602920114,"upper_bound":706.8835396159966},"point_estimate":504.30406448431313,"standard_error":86.89441845046551},"slope":{"confidence_interval":{"confidence_level":0.95,"lower_bound":269055.8440279842,"upper_bound":269341.9201159106},"point_estimate":269188.95599601005,"standard_error":73.02115395657566},"std_dev":{"confidence_interval":{"confidence_level":0.95,"lower_bound":626.1391584241924,"upper_bound":2529.7118005118664},"point_estimate":1654.068390018966,"standard_error":502.9825160933647}}