{"mean":{"confidence_interval":{"confidence_level":0.95,"lower_bound":793849.5153540389,"upper_bound":796348.5009895499},"point_estimate":794861.279834698,"standard_error":653.5669725683904},"median":{"confidence_interval":{"confidence_level":0.95,"lower_bound":793198.7231670446,"upper_bound":794504.8611111111},"point_estimate":793569.742845787,"standard_error":378.478294805052},"median_abs_dev":{"confidence_interval":{"confidence_level":0.95,"lower_bound":1496.6006594300638,"upper_bound":2470.514245289535},"point_estimate":1974.360960576963,"standard_error":247.29492945470267},"slope":{"confidence_interval":{"confidence_level":0.95,"lower_bound":793963.6474759384,"upper_bound":794900.6752697311},"point_estimate":794451.5475439633,"standard_error":239.33625594288495},"std_dev":{"confidence_interval":{"confidence_level":0.95,"lower_bound":2023.506411348523,"upper_bound":10643.165649221737},"point_estimate":6579.849568601436,"standard_error":2629.3305478160837}}